{
  "_comment": "Generated by scripts/build-alias-shards.mjs from data/search/aliases.json (the authoring master). Runtime shard for group Z: app.js ensureAliases fetches every group's shard in parallel on first search interaction. Do not edit by hand; edit the master and rerun the script.",
  "_updated": "2026-07-17",
  "aliases": [
    {"term":"guy wire","target":"guy-wire-tension","kind":"industry"},
    {"term":"guy tension","target":"guy-wire-tension","kind":"industry"},
    {"term":"down guy","target":"guy-wire-tension","kind":"industry"},
    {"term":"mast guy","target":"guy-wire-tension","kind":"industry"},
    {"term":"guy anchor","target":"guy-wire-tension","kind":"industry"},
    {"term":"reeving","target":"reeving-parts-of-line","kind":"industry"},
    {"term":"parts of line","target":"reeving-parts-of-line","kind":"industry"},
    {"term":"block and tackle pull","target":"reeving-parts-of-line","kind":"industry"},
    {"term":"hauling line pull","target":"reeving-parts-of-line","kind":"industry"},
    {"term":"sheave efficiency","target":"reeving-parts-of-line","kind":"industry"},
    {"term":"crane load radius","target":"crane-load-radius-boom","kind":"industry"},
    {"term":"boom angle radius","target":"crane-load-radius-boom","kind":"industry"},
    {"term":"load radius from boom angle","target":"crane-load-radius-boom","kind":"industry"},
    {"term":"boom tip height","target":"crane-load-radius-boom","kind":"industry"},
    {"term":"crane boom geometry","target":"crane-load-radius-boom","kind":"industry"},
    {"term":"center of gravity","target":"cg-load-share","kind":"industry"},
    {"term":"pick point","target":"cg-load-share","kind":"industry"},
    {"term":"load share","target":"cg-load-share","kind":"industry"},
    {"term":"two point lift","target":"cg-load-share","kind":"redirect"},
    {"term":"unbalanced load","target":"cg-load-share","kind":"adjacent"},
    {"term":"load chart","target":"crane-net-capacity","kind":"industry"},
    {"term":"net capacity","target":"crane-net-capacity","kind":"industry"},
    {"term":"deduction","target":"crane-net-capacity","kind":"adjacent"},
    {"term":"percent of chart","target":"crane-net-capacity","kind":"redirect"},
    {"term":"critical lift","target":"crane-net-capacity","kind":"adjacent"},
    {"term":"outrigger pressure","target":"crane-ground-bearing","kind":"industry"},
    {"term":"ground bearing","target":"crane-ground-bearing","kind":"industry"},
    {"term":"crane mat","target":"crane-ground-bearing","kind":"redirect"},
    {"term":"cribbing","target":"crane-ground-bearing","kind":"adjacent"},
    {"term":"soil bearing","target":"crane-ground-bearing","kind":"adjacent"},
    {"term":"d over d","target":"sling-d-d-efficiency","kind":"industry"},
    {"term":"bend efficiency","target":"sling-d-d-efficiency","kind":"industry"},
    {"term":"wire rope sling","target":"sling-d-d-efficiency","kind":"redirect"},
    {"term":"choker","target":"sling-d-d-efficiency","kind":"adjacent"},
    {"term":"wind load","target":"wind-on-load","kind":"industry"},
    {"term":"sail area","target":"wind-on-load","kind":"industry"},
    {"term":"swing","target":"wind-on-load","kind":"adjacent"},
    {"term":"tag line","target":"tagline-force","kind":"industry"},
    {"term":"tagline","target":"tagline-force","kind":"redirect"},
    {"term":"load control","target":"tagline-force","kind":"adjacent"},
    {"term":"tandem lift","target":"tandem-lift-share","kind":"industry"},
    {"term":"two crane","target":"tandem-lift-share","kind":"industry"},
    {"term":"dual crane","target":"tandem-lift-share","kind":"redirect"},
    {"term":"multi crane","target":"tandem-lift-share","kind":"adjacent"},
    {"term":"shackle","target":"shackle-eyebolt-wll","kind":"industry"},
    {"term":"eye bolt","target":"shackle-eyebolt-wll","kind":"industry"},
    {"term":"hoist ring","target":"shackle-eyebolt-wll","kind":"adjacent"},
    {"term":"side load","target":"shackle-eyebolt-wll","kind":"redirect"},
    {"term":"wll","target":"shackle-eyebolt-wll","kind":"industry"},
    {"term":"derate","target":"shackle-eyebolt-wll","kind":"adjacent"},
    {"term":"spreader bar","target":"spreader-beam","kind":"industry"},
    {"term":"spreader beam height","target":"spreader-beam-min-height","kind":"industry"},
    {"term":"minimum headroom spreader","target":"spreader-beam-min-height","kind":"redirect"},
    {"term":"spreader min height","target":"spreader-beam-min-height","kind":"adjacent"},
    {"term":"how much headroom for spreader","target":"spreader-beam-min-height","kind":"adjacent"},
    {"term":"top point height spreader","target":"spreader-beam-min-height","kind":"adjacent"},
    {"term":"lifting beam","target":"spreader-beam","kind":"industry"},
    {"term":"below the hook","target":"spreader-beam","kind":"redirect"},
    {"term":"spreader","target":"spreader-beam","kind":"adjacent"},
    {"term":"forklift capacity","target":"forklift-capacity-derate","kind":"industry"},
    {"term":"load center","target":"forklift-capacity-derate","kind":"industry"},
    {"term":"data plate","target":"forklift-capacity-derate","kind":"redirect"},
    {"term":"attachment","target":"forklift-capacity-derate","kind":"adjacent"},
    {"term":"forklift derate","target":"forklift-capacity-derate","kind":"adjacent"},
    {"term":"rollers","target":"roller-jack-force","kind":"industry"},
    {"term":"skates","target":"roller-jack-force","kind":"industry"},
    {"term":"machinery move","target":"roller-jack-force","kind":"redirect"},
    {"term":"jacking","target":"roller-jack-force","kind":"adjacent"},
    {"term":"push force","target":"roller-jack-force","kind":"adjacent"},
    {"term":"chain hoist","target":"chain-lever-hoist","kind":"industry"},
    {"term":"come along","target":"chain-lever-hoist","kind":"industry"},
    {"term":"lever hoist","target":"chain-lever-hoist","kind":"industry"},
    {"term":"chain fall","target":"chain-lever-hoist","kind":"redirect"},
    {"term":"snatch block","target":"block-redirect-load","kind":"industry"},
    {"term":"max redirect angle","target":"block-redirect-max-angle","kind":"industry"},
    {"term":"block redirect max angle","target":"block-redirect-max-angle","kind":"redirect"},
    {"term":"how far can I turn a block","target":"block-redirect-max-angle","kind":"adjacent"},
    {"term":"max angle for block","target":"block-redirect-max-angle","kind":"adjacent"},
    {"term":"redirect angle for wll","target":"block-redirect-max-angle","kind":"adjacent"},
    {"term":"redirect","target":"block-redirect-load","kind":"redirect"},
    {"term":"block load","target":"block-redirect-load","kind":"adjacent"},
    {"term":"sheave","target":"block-redirect-load","kind":"adjacent"},
    {"term":"multi leg sling","target":"multi-leg-sling","kind":"industry"},
    {"term":"4 leg sling","target":"multi-leg-sling","kind":"industry"},
    {"term":"3 leg sling","target":"multi-leg-sling","kind":"adjacent"},
    {"term":"load per leg","target":"multi-leg-sling","kind":"adjacent"},
    {"term":"sling leg tension","target":"multi-leg-sling","kind":"adjacent"},
    {"term":"wire rope breaking strength","target":"wire-rope-strength","kind":"industry"},
    {"term":"wire rope mbs","target":"wire-rope-strength","kind":"adjacent"},
    {"term":"rope wll","target":"wire-rope-strength","kind":"adjacent"},
    {"term":"cable strength","target":"wire-rope-strength","kind":"redirect"},
    {"term":"cable sag","target":"spanline-sag-tension","kind":"industry"},
    {"term":"spanline","target":"spanline-sag-tension","kind":"industry"},
    {"term":"highline","target":"spanline-sag-tension","kind":"industry"},
    {"term":"tramline","target":"spanline-sag-tension","kind":"adjacent"},
    {"term":"catenary sag","target":"spanline-sag-tension","kind":"adjacent"},
    {"term":"wire rope span","target":"spanline-sag-tension","kind":"adjacent"},
    {"term":"span tension","target":"spanline-sag-tension","kind":"industry"},
    {"term":"guy wire tension","target":"spanline-sag-tension","kind":"adjacent"},
    {"term":"minimum sag","target":"spanline-sag-for-tension","kind":"industry"},
    {"term":"sag for a tension limit","target":"spanline-sag-for-tension","kind":"industry"},
    {"term":"how much sag do i need","target":"spanline-sag-for-tension","kind":"adjacent"},
    {"term":"sag for rope wll","target":"spanline-sag-for-tension","kind":"adjacent"},
    {"term":"how tight can i pull a span","target":"spanline-sag-for-tension","kind":"adjacent"},
    {"term":"bridle tension","target":"bridle-leg-tension","kind":"industry"},
    {"term":"two leg bridle","target":"bridle-leg-tension","kind":"industry"},
    {"term":"asymmetric bridle","target":"bridle-leg-tension","kind":"industry"},
    {"term":"bridle leg load","target":"bridle-leg-tension","kind":"redirect"},
    {"term":"rigging bridle geometry","target":"bridle-leg-tension","kind":"adjacent"},
    {"term":"apex load split","target":"bridle-leg-tension","kind":"redirect"},
    {"term":"shallow bridle","target":"bridle-leg-tension","kind":"adjacent"},
    {"term":"bridle horizontal pull","target":"bridle-leg-tension","kind":"adjacent"},
    {"term":"winch line pull","target":"winch-drum-line-pull","kind":"industry"},
    {"term":"drum line pull","target":"winch-drum-line-pull","kind":"industry"},
    {"term":"winch layer derate","target":"winch-drum-line-pull","kind":"redirect"},
    {"term":"bare drum rating","target":"winch-drum-line-pull","kind":"industry"},
    {"term":"winch capacity by layer","target":"winch-drum-line-pull","kind":"redirect"},
    {"term":"wire rope drum","target":"winch-drum-line-pull","kind":"adjacent"},
    {"term":"line speed layer","target":"winch-drum-line-pull","kind":"adjacent"},
    {"term":"winch stall","target":"winch-drum-line-pull","kind":"adjacent"},
    {"term":"outrigger reaction","target":"crane-outrigger-reaction","kind":"industry"},
    {"term":"crane outrigger load","target":"crane-outrigger-reaction","kind":"industry"},
    {"term":"over corner outrigger","target":"crane-outrigger-reaction","kind":"redirect"},
    {"term":"crane mat load","target":"crane-outrigger-reaction","kind":"adjacent"},
    {"term":"outrigger pad force","target":"crane-outrigger-reaction","kind":"adjacent"},
    {"term":"crane overturning","target":"crane-outrigger-reaction","kind":"adjacent"},
    {"term":"maximum outrigger","target":"crane-outrigger-reaction","kind":"redirect"},
    {"term":"boom over corner","target":"crane-outrigger-reaction","kind":"redirect"},
    {"term":"lifting lug","target":"lifting-lug-design","kind":"industry"},
    {"term":"padeye","target":"lifting-lug-design","kind":"industry"},
    {"term":"pin connected plate","target":"lifting-lug-design","kind":"redirect"},
    {"term":"asme bth-1","target":"lifting-lug-design","kind":"industry"},
    {"term":"lug bearing tearout","target":"lifting-lug-design","kind":"adjacent"},
    {"term":"lug design","target":"lifting-lug-design","kind":"industry"},
    {"term":"hole edge distance lug","target":"lifting-lug-design","kind":"adjacent"},
    {"term":"shackle lug","target":"lifting-lug-design","kind":"adjacent"},
    {"term":"how much weight on each pick point in a two point lift","target":"cg-load-share","kind":"question"},
    {"term":"load split between two crane hooks","target":"cg-load-share","kind":"question"},
    {"term":"where to set the picks on an offset load","target":"cg-load-share","kind":"question"},
    {"term":"how much of the load goes to each sling","target":"cg-load-share","kind":"question"},
    {"term":"is the center of gravity outside my pick points","target":"cg-load-share","kind":"question"},
    {"term":"how uneven is the load between two lift points","target":"cg-load-share","kind":"question"},
    {"term":"weight on each end of a lifted beam","target":"cg-load-share","kind":"question"},
    {"term":"how far off center can i pick a load","target":"cg-load-share","kind":"question"},
    {"term":"load on the near hook with offset cg","target":"cg-load-share","kind":"question"},
    {"term":"percent imbalance on a two point pick","target":"cg-load-share","kind":"question"},
    {"term":"how to share a load across two pick points","target":"cg-load-share","kind":"question"},
    {"term":"pick point spacing for an unbalanced beam","target":"cg-load-share","kind":"question"},
    {"term":"how much can the crane pick after deductions","target":"crane-net-capacity","kind":"question"},
    {"term":"net hook capacity after block and jib","target":"crane-net-capacity","kind":"question"},
    {"term":"how much weight off the load chart after rigging","target":"crane-net-capacity","kind":"question"},
    {"term":"what percent of chart is my lift","target":"crane-net-capacity","kind":"question"},
    {"term":"is this a critical lift over 75 percent","target":"crane-net-capacity","kind":"question"},
    {"term":"deduct hook block and wire rope from capacity","target":"crane-net-capacity","kind":"question"},
    {"term":"how much lift left after the jib deduction","target":"crane-net-capacity","kind":"question"},
    {"term":"total hook load vs net capacity","target":"crane-net-capacity","kind":"question"},
    {"term":"am i over 90 percent of the crane chart","target":"crane-net-capacity","kind":"question"},
    {"term":"crane capacity minus attachment weights","target":"crane-net-capacity","kind":"question"},
    {"term":"how to figure net pick after deductions","target":"crane-net-capacity","kind":"question"},
    {"term":"available capacity on the hook for a pick","target":"crane-net-capacity","kind":"question"},
    {"term":"what size mat under a crane outrigger","target":"crane-ground-bearing","kind":"question"},
    {"term":"outrigger pad size for soft ground","target":"crane-ground-bearing","kind":"question"},
    {"term":"psi under the outrigger float","target":"crane-ground-bearing","kind":"question"},
    {"term":"crawler track pressure on the soil","target":"crane-ground-bearing","kind":"question"},
    {"term":"mat area needed to meet allowable bearing","target":"crane-ground-bearing","kind":"question"},
    {"term":"will the ground hold the crane","target":"crane-ground-bearing","kind":"question"},
    {"term":"dunnage size under an outrigger","target":"crane-ground-bearing","kind":"question"},
    {"term":"timber mat sizing for a heavy pick","target":"crane-ground-bearing","kind":"question"},
    {"term":"outrigger pressure vs allowable psf","target":"crane-ground-bearing","kind":"question"},
    {"term":"crane pad bearing check","target":"crane-ground-bearing","kind":"question"},
    {"term":"how big should the cribbing stack be","target":"crane-ground-bearing","kind":"question"},
    {"term":"float area required for the soil","target":"crane-ground-bearing","kind":"question"},
    {"term":"capacity loss bending a sling around a shackle","target":"sling-d-d-efficiency","kind":"question"},
    {"term":"wll reduction from a small diameter bend","target":"sling-d-d-efficiency","kind":"question"},
    {"term":"sling strength around a small pin","target":"sling-d-d-efficiency","kind":"question"},
    {"term":"how much does a tight bend weaken wire rope","target":"sling-d-d-efficiency","kind":"question"},
    {"term":"basket hitch around small pipe capacity","target":"sling-d-d-efficiency","kind":"question"},
    {"term":"rope bent over a sheave strength loss","target":"sling-d-d-efficiency","kind":"question"},
    {"term":"efficiency of a sling choked on itself","target":"sling-d-d-efficiency","kind":"question"},
    {"term":"rated capacity with a sharp bend point","target":"sling-d-d-efficiency","kind":"question"},
    {"term":"wrtb curve bend factor","target":"sling-d-d-efficiency","kind":"question"},
    {"term":"sling derate for bend diameter ratio","target":"sling-d-d-efficiency","kind":"question"},
    {"term":"choking reduces capacity how much","target":"sling-d-d-efficiency","kind":"question"},
    {"term":"how much does wind push a suspended load","target":"wind-on-load","kind":"question"},
    {"term":"crane pick in 20 mph wind","target":"wind-on-load","kind":"question"},
    {"term":"lateral force on a hanging load in wind","target":"wind-on-load","kind":"question"},
    {"term":"load swing angle from wind speed","target":"wind-on-load","kind":"question"},
    {"term":"wind speed limit for a lift","target":"wind-on-load","kind":"question"},
    {"term":"velocity pressure on a lifted panel","target":"wind-on-load","kind":"question"},
    {"term":"gust force on a tilt-up panel pick","target":"wind-on-load","kind":"question"},
    {"term":"can we lift in this wind","target":"wind-on-load","kind":"question"},
    {"term":"drag force on a load in the breeze","target":"wind-on-load","kind":"question"},
    {"term":"wind pushing the load off vertical","target":"wind-on-load","kind":"question"},
    {"term":"shape coefficient wind force on a lift","target":"wind-on-load","kind":"question"},
    {"term":"max wind speed to lift a panel","target":"max-wind-speed-for-lift","kind":"question"},
    {"term":"wind limit for crane pick","target":"max-wind-speed-for-lift","kind":"question"},
    {"term":"when to stop lifting for wind","target":"max-wind-speed-for-lift","kind":"question"},
    {"term":"shutdown wind speed for load swing","target":"max-wind-speed-for-lift","kind":"question"},
    {"term":"wind speed for 5 degree swing","target":"max-wind-speed-for-lift","kind":"question"},
    {"term":"how many people to hold a tag rope","target":"tagline-force","kind":"question"},
    {"term":"pull needed to steady a swinging load","target":"tagline-force","kind":"question"},
    {"term":"rope tension to control load rotation","target":"tagline-force","kind":"question"},
    {"term":"handlers needed on a steadying line","target":"tagline-force","kind":"question"},
    {"term":"when to use a mechanical tag winch","target":"tagline-force","kind":"question"},
    {"term":"force on the tag rope in wind","target":"tagline-force","kind":"question"},
    {"term":"safe pull per person on a control rope","target":"tagline-force","kind":"question"},
    {"term":"steadying line tension for a crane pick","target":"tagline-force","kind":"question"},
    {"term":"keeping a suspended load from spinning","target":"tagline-force","kind":"question"},
    {"term":"crew count to control a hanging load","target":"tagline-force","kind":"question"},
    {"term":"tag rope angle and pull force","target":"tagline-force","kind":"question"},
    {"term":"load split between two cranes","target":"tandem-lift-share","kind":"question"},
    {"term":"each crane share from the center of gravity","target":"tandem-lift-share","kind":"question"},
    {"term":"how much does each crane carry","target":"tandem-lift-share","kind":"question"},
    {"term":"cg offset load distribution on a dual pick","target":"tandem-lift-share","kind":"question"},
    {"term":"derated allowable for a two crane pick","target":"tandem-lift-share","kind":"question"},
    {"term":"lifting a vessel with two cranes together","target":"tandem-lift-share","kind":"question"},
    {"term":"unequal load share between cranes","target":"tandem-lift-share","kind":"question"},
    {"term":"critical lift on two hooks","target":"tandem-lift-share","kind":"question"},
    {"term":"percent of load on each hook","target":"tandem-lift-share","kind":"question"},
    {"term":"tailing crane load share","target":"tandem-lift-share","kind":"question"},
    {"term":"planning numbers for a two crane pick","target":"tandem-lift-share","kind":"question"},
    {"term":"shackle capacity at an angle","target":"shackle-eyebolt-wll","kind":"question"},
    {"term":"eye bolt pull at 45 degrees","target":"shackle-eyebolt-wll","kind":"question"},
    {"term":"angular loading reduction on an eye bolt","target":"shackle-eyebolt-wll","kind":"question"},
    {"term":"side pull on a shackle capacity","target":"shackle-eyebolt-wll","kind":"question"},
    {"term":"shoulder eye bolt angle rating","target":"shackle-eyebolt-wll","kind":"question"},
    {"term":"swivel hoist ring vs eye bolt at an angle","target":"shackle-eyebolt-wll","kind":"question"},
    {"term":"reduced capacity for an angled pull","target":"shackle-eyebolt-wll","kind":"question"},
    {"term":"can i side load this shackle","target":"shackle-eyebolt-wll","kind":"question"},
    {"term":"eye bolt rating pass fail at an angle","target":"shackle-eyebolt-wll","kind":"question"},
    {"term":"hardware derate for pull angle","target":"shackle-eyebolt-wll","kind":"question"},
    {"term":"in-line vs angled shackle rating","target":"shackle-eyebolt-wll","kind":"question"},
    {"term":"top sling tension on a spreader rig","target":"spreader-beam","kind":"question"},
    {"term":"compression in the spreader bar","target":"spreader-beam","kind":"question"},
    {"term":"bending moment in a lifting beam","target":"spreader-beam","kind":"question"},
    {"term":"headroom needed for a wide pick","target":"spreader-beam","kind":"question"},
    {"term":"spreader vs beam which to use","target":"spreader-beam","kind":"question"},
    {"term":"sling tension above the bar","target":"spreader-beam","kind":"question"},
    {"term":"bth-1 beam moment check","target":"spreader-beam","kind":"question"},
    {"term":"lifting a long load from one hook","target":"spreader-beam","kind":"question"},
    {"term":"axial force in the bar between slings","target":"spreader-beam","kind":"question"},
    {"term":"beam under the hook bending check","target":"spreader-beam","kind":"question"},
    {"term":"rigging geometry for a wide load pick","target":"spreader-beam","kind":"question"},
    {"term":"forklift rating with a long pallet","target":"forklift-capacity-derate","kind":"question"},
    {"term":"how much can my forklift lift with a long load","target":"forklift-capacity-derate","kind":"question"},
    {"term":"fork truck capacity loss with an oversized pallet","target":"forklift-capacity-derate","kind":"question"},
    {"term":"net capacity with an attachment on the forks","target":"forklift-capacity-derate","kind":"question"},
    {"term":"lifting a 48 inch deep crate with a forklift","target":"forklift-capacity-derate","kind":"question"},
    {"term":"nameplate rating vs actual lift capacity","target":"forklift-capacity-derate","kind":"question"},
    {"term":"can my 5000 lb forklift pick this crate","target":"forklift-capacity-derate","kind":"question"},
    {"term":"capacity drop when the load sticks out","target":"forklift-capacity-derate","kind":"question"},
    {"term":"derating forks for extended loads","target":"forklift-capacity-derate","kind":"question"},
    {"term":"fork truck margin check on a heavy pallet","target":"forklift-capacity-derate","kind":"question"},
    {"term":"lift truck rating with the weight far forward","target":"forklift-capacity-derate","kind":"question"},
    {"term":"force to push a machine on skates","target":"roller-jack-force","kind":"question"},
    {"term":"how hard to push a 10000 lb load on rollers","target":"roller-jack-force","kind":"question"},
    {"term":"breakaway force moving equipment","target":"roller-jack-force","kind":"question"},
    {"term":"pushing a safe up a ramp force","target":"roller-jack-force","kind":"question"},
    {"term":"moving heavy machinery by hand force needed","target":"roller-jack-force","kind":"question"},
    {"term":"skate count for the machine weight","target":"roller-jack-force","kind":"question"},
    {"term":"rolling resistance on machinery dollies","target":"roller-jack-force","kind":"question"},
    {"term":"toe jack and skate move planning","target":"roller-jack-force","kind":"question"},
    {"term":"push needed on a slight grade","target":"roller-jack-force","kind":"question"},
    {"term":"how many machine skates do i need","target":"roller-jack-force","kind":"question"},
    {"term":"crew push force for an equipment move","target":"roller-jack-force","kind":"question"},
    {"term":"hand pull to lift a ton with a chain block","target":"chain-lever-hoist","kind":"question"},
    {"term":"how much chain to pull to raise the load a foot","target":"chain-lever-hoist","kind":"question"},
    {"term":"effort on the hand chain","target":"chain-lever-hoist","kind":"question"},
    {"term":"lever puller force needed","target":"chain-lever-hoist","kind":"question"},
    {"term":"chain block mechanical advantage","target":"chain-lever-hoist","kind":"question"},
    {"term":"ratchet puller effort to move a load","target":"chain-lever-hoist","kind":"question"},
    {"term":"hand chain travel per foot of lift","target":"chain-lever-hoist","kind":"question"},
    {"term":"can a half ton hoist lift this load","target":"chain-lever-hoist","kind":"question"},
    {"term":"manual hoist pull force","target":"chain-lever-hoist","kind":"question"},
    {"term":"chain block sizing for a lift","target":"chain-lever-hoist","kind":"question"},
    {"term":"hoist rated limit pass fail check","target":"chain-lever-hoist","kind":"question"},
    {"term":"force on a block when the line turns","target":"block-redirect-load","kind":"question"},
    {"term":"anchor load at a rope redirect point","target":"block-redirect-load","kind":"question"},
    {"term":"doubled force at a 180 degree turn","target":"block-redirect-load","kind":"question"},
    {"term":"resultant on a turning block anchor","target":"block-redirect-load","kind":"question"},
    {"term":"pulley anchor force with two line parts","target":"block-redirect-load","kind":"question"},
    {"term":"load on the redirect during a winch pull","target":"block-redirect-load","kind":"question"},
    {"term":"why the block sees twice the line pull","target":"block-redirect-load","kind":"question"},
    {"term":"angle between rope parts and block force","target":"block-redirect-load","kind":"question"},
    {"term":"rigging point load when the line changes direction","target":"block-redirect-load","kind":"question"},
    {"term":"sizing the anchor for a turn block","target":"block-redirect-load","kind":"question"},
    {"term":"deflection angle force on a pulley","target":"block-redirect-load","kind":"question"},
    {"term":"tension in each leg of a four leg lift","target":"multi-leg-sling","kind":"question"},
    {"term":"why only two legs carry the load","target":"multi-leg-sling","kind":"question"},
    {"term":"sling angle load factor per leg","target":"multi-leg-sling","kind":"question"},
    {"term":"leg tension at 60 degrees","target":"multi-leg-sling","kind":"question"},
    {"term":"b30.9 two legs carry assumption","target":"multi-leg-sling","kind":"question"},
    {"term":"share of the load on each leg","target":"multi-leg-sling","kind":"question"},
    {"term":"1 over sine load factor","target":"multi-leg-sling","kind":"question"},
    {"term":"quad sling tension calculation","target":"multi-leg-sling","kind":"question"},
    {"term":"rigid load two leg rule","target":"multi-leg-sling","kind":"question"},
    {"term":"leg load at a flat sling angle","target":"multi-leg-sling","kind":"question"},
    {"term":"picking a crate with a four leg set","target":"multi-leg-sling","kind":"question"},
    {"term":"breaking strength of 1/2 inch wire rope","target":"wire-rope-strength","kind":"question"},
    {"term":"estimating rope strength from diameter","target":"wire-rope-strength","kind":"question"},
    {"term":"ips 6x19 strength by size","target":"wire-rope-strength","kind":"question"},
    {"term":"diameter squared times constant rope strength","target":"wire-rope-strength","kind":"question"},
    {"term":"working load at a 5 to 1 design factor","target":"wire-rope-strength","kind":"question"},
    {"term":"safe working load from breaking strength","target":"wire-rope-strength","kind":"question"},
    {"term":"tons a 3/4 cable can hold","target":"wire-rope-strength","kind":"question"},
    {"term":"minimum break strength of unmarked rope","target":"wire-rope-strength","kind":"question"},
    {"term":"field estimate of wire rope capacity","target":"wire-rope-strength","kind":"question"},
    {"term":"design factor to working load rope","target":"wire-rope-strength","kind":"question"},
    {"term":"rope size for a required working load","target":"wire-rope-diameter-for-wll","kind":"question"},
    {"term":"wire rope diameter for load","target":"wire-rope-diameter-for-wll","kind":"question"},
    {"term":"what size cable for 5 tons","target":"wire-rope-diameter-for-wll","kind":"question"},
    {"term":"pick rope size for wll","target":"wire-rope-diameter-for-wll","kind":"question"},
    {"term":"cable diameter from working load limit","target":"wire-rope-diameter-for-wll","kind":"question"},
    {"term":"tension in a tight cable span","target":"spanline-sag-tension","kind":"question"},
    {"term":"pulling a line tighter raises tension how much","target":"spanline-sag-tension","kind":"question"},
    {"term":"sag needed to keep the tension low","target":"spanline-sag-tension","kind":"question"},
    {"term":"messenger wire tension from sag","target":"spanline-sag-tension","kind":"question"},
    {"term":"anchor load on a zip line span","target":"spanline-sag-tension","kind":"question"},
    {"term":"horizontal tension from span and sag","target":"spanline-sag-tension","kind":"question"},
    {"term":"tension in a rope stretched between two points","target":"spanline-sag-tension","kind":"question"},
    {"term":"100 ft span with 2 ft of sag tension","target":"spanline-sag-tension","kind":"question"},
    {"term":"why a taut span overloads the anchors","target":"spanline-sag-tension","kind":"question"},
    {"term":"developed length of a sagging cable","target":"spanline-sag-tension","kind":"question"},
    {"term":"support tension at the end of a span","target":"spanline-sag-tension","kind":"question"},
    {"term":"clothesline effect tension","target":"spanline-sag-tension","kind":"question"},
    {"term":"uneven bridle which leg carries more","target":"bridle-leg-tension","kind":"question"},
    {"term":"leg tension from run and rise","target":"bridle-leg-tension","kind":"question"},
    {"term":"bridle to two beams at different heights","target":"bridle-leg-tension","kind":"question"},
    {"term":"steep leg vs shallow leg force","target":"bridle-leg-tension","kind":"question"},
    {"term":"point load split between bridle legs","target":"bridle-leg-tension","kind":"question"},
    {"term":"horizontal reaction on the beam from a bridle","target":"bridle-leg-tension","kind":"question"},
    {"term":"why a flat bridle overloads its legs","target":"bridle-leg-tension","kind":"question"},
    {"term":"arena rigging bridle math","target":"bridle-leg-tension","kind":"question"},
    {"term":"deadhang vs bridle leg force","target":"bridle-leg-tension","kind":"question"},
    {"term":"offset apex leg tension","target":"bridle-leg-tension","kind":"question"},
    {"term":"bridle angles and leg loads","target":"bridle-leg-tension","kind":"question"},
    {"term":"winch pull on the top layer","target":"winch-drum-line-pull","kind":"question"},
    {"term":"why my winch is weaker with a full drum","target":"winch-drum-line-pull","kind":"question"},
    {"term":"rated pull first wrap vs last wrap","target":"winch-drum-line-pull","kind":"question"},
    {"term":"line pull drop per rope layer","target":"winch-drum-line-pull","kind":"question"},
    {"term":"full drum vs empty drum pulling power","target":"winch-drum-line-pull","kind":"question"},
    {"term":"winch speeds up as the drum fills","target":"winch-drum-line-pull","kind":"question"},
    {"term":"pull rating at the third layer","target":"winch-drum-line-pull","kind":"question"},
    {"term":"effective drum diameter with rope layers","target":"winch-drum-line-pull","kind":"question"},
    {"term":"12000 lb winch actual pull on a full spool","target":"winch-drum-line-pull","kind":"question"},
    {"term":"planning a recovery pull by layer","target":"winch-drum-line-pull","kind":"question"},
    {"term":"rope layer effect on pulling capacity","target":"winch-drum-line-pull","kind":"question"},
    {"term":"load on one outrigger during a pick","target":"crane-outrigger-reaction","kind":"question"},
    {"term":"worst case pad load swinging over the corner","target":"crane-outrigger-reaction","kind":"question"},
    {"term":"how much weight goes into one float","target":"crane-outrigger-reaction","kind":"question"},
    {"term":"outrigger force from load and radius","target":"crane-outrigger-reaction","kind":"question"},
    {"term":"corner load when the boom swings","target":"crane-outrigger-reaction","kind":"question"},
    {"term":"single pad reaction on a heavy pick","target":"crane-outrigger-reaction","kind":"question"},
    {"term":"counterweight effect on pad loads","target":"crane-outrigger-reaction","kind":"question"},
    {"term":"moment from the radius to pad force","target":"crane-outrigger-reaction","kind":"question"},
    {"term":"more than half the crane on one pad","target":"crane-outrigger-reaction","kind":"question"},
    {"term":"reaction at each outrigger for the lift plan","target":"crane-outrigger-reaction","kind":"question"},
    {"term":"pad load input for mat sizing","target":"crane-outrigger-reaction","kind":"question"},
    {"term":"pin hole strength check on a lug","target":"lifting-lug-design","kind":"question"},
    {"term":"tear out at the pin hole","target":"lifting-lug-design","kind":"question"},
    {"term":"bearing stress at the shackle pin","target":"lifting-lug-design","kind":"question"},
    {"term":"net section tension through the hole","target":"lifting-lug-design","kind":"question"},
    {"term":"double plane shear at a pad eye","target":"lifting-lug-design","kind":"question"},
    {"term":"pin hole failure modes in a plate","target":"lifting-lug-design","kind":"question"},
    {"term":"capacity of a welded lifting ear","target":"lifting-lug-design","kind":"question"},
    {"term":"dcr check on a lifting attachment","target":"lifting-lug-design","kind":"question"},
    {"term":"plate thickness for pin bearing","target":"lifting-lug-design","kind":"question"},
    {"term":"edge distance tear out check","target":"lifting-lug-design","kind":"question"},
    {"term":"bth-1 pin connected plate checks","target":"lifting-lug-design","kind":"question"},
    {"term":"pad eye governing failure mode","target":"lifting-lug-design","kind":"question"},
    {"term":"three point bridle","target":"three-point-bridle","kind":"industry"},
    {"term":"three leg bridle","target":"three-point-bridle","kind":"industry"},
    {"term":"3 leg bridle tension","target":"three-point-bridle","kind":"redirect"},
    {"term":"bridle apex triangle","target":"three-point-bridle","kind":"adjacent"},
    {"term":"arena rigging bridle","target":"three-point-bridle","kind":"adjacent"},
    {"term":"tension in each leg of a three point bridle","target":"three-point-bridle","kind":"question"},
    {"term":"three leg bridle leg loads","target":"three-point-bridle","kind":"question"},
    {"term":"solve a 3d rigging bridle","target":"three-point-bridle","kind":"question"},
    {"term":"how much does each leg of a three point bridle carry","target":"three-point-bridle","kind":"question"},
    {"term":"bridle with three attachment points","target":"three-point-bridle","kind":"question"},
    {"term":"beam clamp","target":"beam-clamp-side-pull","kind":"industry"},
    {"term":"wire rope clips","target":"wire-rope-clips","kind":"industry"},
    {"term":"how many wire rope clips","target":"wire-rope-clips","kind":"industry"},
    {"term":"u-bolt clips","target":"wire-rope-clips","kind":"industry"},
    {"term":"cable clip spacing","target":"wire-rope-clips","kind":"adjacent"},
    {"term":"never saddle a dead horse","target":"wire-rope-clips","kind":"adjacent"},
    {"term":"side pull","target":"beam-clamp-side-pull","kind":"industry"},
    {"term":"beam clamp side pull","target":"beam-clamp-side-pull","kind":"industry"},
    {"term":"clamp side load","target":"beam-clamp-side-pull","kind":"adjacent"},
    {"term":"horizontal beam reaction","target":"beam-clamp-side-pull","kind":"redirect"},
    {"term":"can a beam clamp take side pull","target":"beam-clamp-side-pull","kind":"question"},
    {"term":"bridle leg force on a beam clamp","target":"beam-clamp-side-pull","kind":"question"},
    {"term":"vertical and horizontal components of a rigging leg","target":"beam-clamp-side-pull","kind":"question"},
    {"term":"check a beam clamp against its wll","target":"beam-clamp-side-pull","kind":"question"},
    {"term":"side pull on an unrated clamp re rig","target":"beam-clamp-side-pull","kind":"question"},
    {"term":"minimum headroom for a spreader beam","target":"spreader-beam-min-height","kind":"question"},
    {"term":"how much height for a spreader bar","target":"spreader-beam-min-height","kind":"question"},
    {"term":"top point height for a spreader","target":"spreader-beam-min-height","kind":"question"},
    {"term":"spreader beam minimum height","target":"spreader-beam-min-height","kind":"question"},
    {"term":"headroom needed above a spreader","target":"spreader-beam-min-height","kind":"question"},
    {"term":"how far can i turn a line through a block","target":"block-redirect-max-angle","kind":"question"},
    {"term":"max redirect angle for a block wll","target":"block-redirect-max-angle","kind":"question"},
    {"term":"biggest direction change on a block","target":"block-redirect-max-angle","kind":"question"},
    {"term":"angle a block can turn a line","target":"block-redirect-max-angle","kind":"question"},
    {"term":"max turn without overloading a block","target":"block-redirect-max-angle","kind":"question"},
    {"term":"minimum sag for a tension limit","target":"spanline-sag-for-tension","kind":"question"},
    {"term":"how much sag to stay under wll","target":"spanline-sag-for-tension","kind":"question"},
    {"term":"least sag before the anchor overloads","target":"spanline-sag-for-tension","kind":"question"},
    {"term":"sag for a rope tension limit","target":"spanline-sag-for-tension","kind":"question"},
    {"term":"how tight can i pull a span line","target":"spanline-sag-for-tension","kind":"question"}
  ]
}
